aasan/__init__.py
files/__init__.py
sarc/__init__.py
Aasan-0.1.2.dist-info/LICENSE
Aasan-0.1.2.dist-info/METADATA
Aasan-0.1.2.dist-info/WHEEL
Aasan-0.1.2.dist-info/top_level.txt
Aasan-0.1.2.dist-info/RECORD
