Metadata-Version: 2.1
Name: Aasan
Version: 0.1.2
Summary: This python package helps make python more easier than it already is.
Home-page: https://github.com/aneeshshukla/aasan
Author: Aneesh Shukla
Classifier: Programming Language :: Python :: 3
Classifier: License :: OSI Approved :: MIT License
Classifier: Operating System :: OS Independent
Requires-Python: >=3.6
License-File: LICENSE
